cloudmetrics/__init__.py
cloudmetrics/_version.py
cloudmetrics/utils.py
cloudmetrics/mask/__init__.py
cloudmetrics/mask/cloud_fraction.py
cloudmetrics/mask/fractal_dimension.py
cloudmetrics/mask/objects.py
cloudmetrics/mask/open_sky.py
cloudmetrics/mask/orientation.py
cloudmetrics/objects/__init__.py
cloudmetrics/objects/label.py
cloudmetrics/objects/metrics/__init__.py
cloudmetrics/objects/metrics/_object_properties.py
cloudmetrics/objects/metrics/cop.py
cloudmetrics/objects/metrics/geometry.py
cloudmetrics/objects/metrics/iorg.py
cloudmetrics/objects/metrics/num_objects.py
cloudmetrics/objects/metrics/scai.py
cloudmetrics/scalar/__init__.py
cloudmetrics/scalar/spectral.py
cloudmetrics/scalar/stats.py
cloudmetrics/scalar/woi.py
tests/__init__.py
tests/cop_examples.py
tests/scai_examples.py
tests/test_cloud_fraction.py
tests/test_cop.py
tests/test_dummy.py
tests/test_fourier.py
tests/test_fractal_dimension.py
tests/test_iorg.py
tests/test_labelled_objects.py
tests/test_nearest_neighbours.py
tests/test_object_scales.py
tests/test_open_sky.py
tests/test_orientation.py
tests/test_scai.py
tests/test_scalar_stats.py
tests/test_utils.py
tests/test_woi.py
cloudmetrics-0.3.0.dist-info/METADATA
cloudmetrics-0.3.0.dist-info/WHEEL
cloudmetrics-0.3.0.dist-info/top_level.txt
cloudmetrics-0.3.0.dist-info/RECORD
