Metadata-Version: 2.1
Name: cloudmetrics
Version: 0.3.0
Summary: Cloud pattern metrics toolkit
Home-page: https://github.com/cloudsci/cloudmetrics
Author: Leif Denby, Martin Janssens
Author-email: l.c.denby@leeds.ac.uk, martin.janssens@wur.nl
Requires-Dist: scipy >=1.4.1
Requires-Dist: PyWavelets >=1.1.1
Requires-Dist: hilbertcurve >=2.0.5
Requires-Dist: scikit-image >=0.16.2
Requires-Dist: scikit-learn >=0.22.1
Requires-Dist: numba >=0.55.2
Requires-Dist: matplotlib >=3.1.3
Requires-Dist: seaborn >=0.10.0
Provides-Extra: dev
Requires-Dist: pytest ; extra == 'dev'
Requires-Dist: nbval ; extra == 'dev'
Requires-Dist: pre-commit ; extra == 'dev'
Requires-Dist: ipython ; extra == 'dev'
Provides-Extra: test
Requires-Dist: pytest ; extra == 'test'
Requires-Dist: nbval ; extra == 'test'
